LICENSE.txt
MANIFEST.in
README.md
setup.py
/Users/dasmith/sites/pyodbc/src/buffer.cpp
/Users/dasmith/sites/pyodbc/src/cnxninfo.cpp
/Users/dasmith/sites/pyodbc/src/connection.cpp
/Users/dasmith/sites/pyodbc/src/cursor.cpp
/Users/dasmith/sites/pyodbc/src/errors.cpp
/Users/dasmith/sites/pyodbc/src/getdata.cpp
/Users/dasmith/sites/pyodbc/src/params.cpp
/Users/dasmith/sites/pyodbc/src/pyodbccompat.cpp
/Users/dasmith/sites/pyodbc/src/pyodbcdbg.cpp
/Users/dasmith/sites/pyodbc/src/pyodbcmodule.cpp
/Users/dasmith/sites/pyodbc/src/row.cpp
/Users/dasmith/sites/pyodbc/src/sqlwchar.cpp
pyodbc_raw.egg-info/PKG-INFO
pyodbc_raw.egg-info/SOURCES.txt
pyodbc_raw.egg-info/dependency_links.txt
pyodbc_raw.egg-info/top_level.txt
src/buffer.cpp
src/buffer.h
src/cnxninfo.cpp
src/cnxninfo.h
src/connection.cpp
src/connection.h
src/cursor.cpp
src/cursor.h
src/dbspecific.h
src/errors.cpp
src/errors.h
src/getdata.cpp
src/getdata.h
src/params.cpp
src/params.h
src/pyodbc.h
src/pyodbccompat.cpp
src/pyodbccompat.h
src/pyodbcdbg.cpp
src/pyodbcmodule.cpp
src/pyodbcmodule.h
src/resource.h
src/row.cpp
src/row.h
src/sqlwchar.cpp
src/sqlwchar.h
src/wrapper.h
tests2/accesstests.py
tests2/dbapi20.py
tests2/dbapitests.py
tests2/empty.accdb
tests2/empty.mdb
tests2/exceltests.py
tests2/freetdstests.py
tests2/informixtests.py
tests2/mysqltests.py
tests2/pgtests.py
tests2/sqlite.db
tests2/sqlitetests.py
tests2/sqlservertests.py
tests2/test.py
tests2/test.xls
tests2/testbase.py
tests2/testutils.py
tests3/accesstests.py
tests3/dbapi20.py
tests3/dbapitests.py
tests3/exceltests.py
tests3/informixtests.py
tests3/mysqltests.py
tests3/pgtests.py
tests3/sqlitetests.py
tests3/sqlservertests.py
tests3/test.py
tests3/testbase.py
tests3/testutils.py