Metadata-Version: 1.1
Name: pyodbc-raw
Version: 3.0.11b17
Summary: DB API Module for ODBC
Home-page: https://github.com/codecloud/pyodbc-raw
Author: David Smith
Author-email: dave@code-cloud.co.uk
License: MIT
Download-URL: https://github.com/codecloud/pyodbc-raw/tarball/raw-output
Platform: UNKNOWN
Classifier: Development Status :: 5 - Production/Stable
Classifier: Intended Audience :: Developers
Classifier: Intended Audience :: System Administrators
Classifier: License :: OSI Approved :: MIT License
Classifier: Operating System :: Microsoft :: Windows
Classifier: Operating System :: POSIX
Classifier: Programming Language :: Python
Classifier: Programming Language :: Python :: 2
Classifier: Programming Language :: Python :: 3
Classifier: Topic :: Database
